texflash/__init__.py
texflash/app.py
texflash/cli.py
texflash/backend/__init__.py
texflash/backend/card.py
texflash/backend/database.py
texflash/backend/parse.py
texflash/backend/source.py
texflash/backend/stats.py
texflash/frontend/__init__.py
texflash/frontend/cards_tab.py
texflash/frontend/sources_tab.py
texflash/frontend/stats_tab.py
texflash-0.1.1.dist-info/LICENSE
texflash-0.1.1.dist-info/METADATA
texflash-0.1.1.dist-info/WHEEL
texflash-0.1.1.dist-info/entry_points.txt
texflash-0.1.1.dist-info/top_level.txt
texflash-0.1.1.dist-info/RECORD
