Metadata-Version: 2.1
Name: texflash
Version: 0.1.1
Summary: A webapp to parse flash cards from .tex file and learn them.
Home-page: https://github.com/ListIndexOutOfRange/texflash
Author: Luc Vedrenne
Author-email: vedrenneluc@gmail.com
Maintainer: Luc Vedrenne
Maintainer-email: vedrenneluc@gmail.com
License: Apache-2.0
Classifier: Development Status :: 3 - Alpha
Classifier: Intended Audience :: Developers
Classifier: Intended Audience :: Science/Research
Classifier: Intended Audience :: Education
Classifier: License :: OSI Approved :: GNU General Public License v3 (GPLv3)
Classifier: Natural Language :: English
Classifier: Programming Language :: Python :: 3
Requires-Python: ~=3.8
License-File: LICENSE
Requires-Dist: numpy (>=1.19.0)
Requires-Dist: streamlit (>=1.13.0)
